tagstr/__init__.py
tagstr/decorator.py
tagstr/importer.py
tagstr/tokenizer.py
tagstr/transform.py
tagstr/types.py
tagstr/utils.py
~tagstr.pth
tagstr-0.2.1.dist-info/METADATA
tagstr-0.2.1.dist-info/WHEEL
tagstr-0.2.1.dist-info/licenses/LICENSE
tagstr-0.2.1.dist-info/RECORD
